TineAutomationToolkit/__init__.py
TineAutomationToolkit/detect/__init__.py
TineAutomationToolkit/detect/detectelement.py
TineAutomationToolkit/detect/flutterfinderwidget.py
TineAutomationToolkit/keywords/__init__.py
TineAutomationToolkit/keywords/capturescreenshot.py
TineAutomationToolkit/keywords/connectionmanagement.py
TineAutomationToolkit/keywords/controlelement.py
TineAutomationToolkit/keywords/convertobject.py
TineAutomationToolkit/keywords/imageprocessing.py
TineAutomationToolkit/keywords/keyevent.py
TineAutomationToolkit/keywords/mongodbcrud.py
TineAutomationToolkit/keywords/scroll.py
TineAutomationToolkit/keywords/toolkitstest.py
TineAutomationToolkit/keywords/touch.py
TineAutomationToolkit/keywords/waitingelement.py
TineAutomationToolkit/utils/__init__.py
TineAutomationToolkit/utils/applicationcache.py
TineAutomationToolkit-1.4.0.dist-info/LICENSE
TineAutomationToolkit-1.4.0.dist-info/METADATA
TineAutomationToolkit-1.4.0.dist-info/WHEEL
TineAutomationToolkit-1.4.0.dist-info/top_level.txt
TineAutomationToolkit-1.4.0.dist-info/RECORD
