Metadata-Version: 2.1
Name: TineAutomationToolkit
Version: 1.4.0
Summary: Test Library for TineAutomationToolkit
Home-page: https://github.com/pornpawit08/TineAutomationToolkit.git
Author: Pornpawit Suttha
Author-email: pornpawit14suttha@gmail.com
License: UNKNOWN
Platform: UNKNOWN
Classifier: Programming Language :: Python :: 3
Classifier: License :: OSI Approved :: MIT License
Classifier: Operating System :: OS Independent
Requires-Python: >=3.6
Requires-Dist: robotframework >=3.0
Requires-Dist: pytz
Requires-Dist: numpy
Requires-Dist: pillow
Requires-Dist: opencv-python
Requires-Dist: matplotlib
